annydict/__init__.py
annydict/annydict.py
annydict-0.1.2.dist-info/LICENSE
annydict-0.1.2.dist-info/METADATA
annydict-0.1.2.dist-info/WHEEL
annydict-0.1.2.dist-info/top_level.txt
annydict-0.1.2.dist-info/RECORD
