Metadata-Version: 2.1
Name: annydict
Version: 0.1.2
Summary: this is in testing phase
Home-page: UNKNOWN
Author: annonymous stark
Author-email: annonymousstark@example.com
License: UNKNOWN
Platform: UNKNOWN
Classifier: Programming Language :: Python :: 3
Classifier: License :: OSI Approved :: MIT License
Classifier: Operating System :: OS Independent
Requires-Python: >=3.6
License-File: LICENSE
